{
  "type": "Feature",
  "stac_version": "1.0.0",
  "stac_extensions": [],
  "id": "00068",
  "geometry": {
    "type": "Polygon",
    "coordinates": [
      [
        [
          28.1249800285983,
          -2.81256378521719
        ],
        [
          32.3437867830783,
          -2.81256378521719
        ],
        [
          32.3437867830783,
          0.0001184
        ],
        [
          28.1249800285983,
          0.0001184
        ],
        [
          28.1249800285983,
          -2.81256378521719
        ]
      ]
    ]
  },
  "bbox": [
    28.1249800285983,
    -2.81256378521719,
    32.3437867830783,
    0.0001184
  ],
  "properties": {
    "datetime": "2025-03-19T00:00:00Z"
  },
  "links": [
    {
      "rel": "root",
      "href": "../../../catalog.json",
      "type": "application/json"
    },
    {
      "rel": "collection",
      "href": "../collection.json",
      "type": "application/json"
    },
    {
      "rel": "parent",
      "href": "../collection.json",
      "type": "application/json"
    }
  ],
  "assets": {
    "parquet-part-00068-591e802d-e569-443e-ac49-12b07aca9379-c000.zstd.parquet": {
      "href": "s3://overturemaps-us-west-2/release/2025-03-19.1/theme=buildings/type=building/part-00068-591e802d-e569-443e-ac49-12b07aca9379-c000.zstd.parquet",
      "type": "application/vnd.apache.parquet"
    }
  },
  "collection": "building"
}