{
  "type": "Feature",
  "stac_version": "1.0.0",
  "stac_extensions": [],
  "id": "00151",
  "geometry": {
    "type": "Polygon",
    "coordinates": [
      [
        [
          80.859281449404,
          25.3123137367258
        ],
        [
          84.3750383637184,
          25.3123137367258
        ],
        [
          84.3750383637184,
          28.125067173193
        ],
        [
          80.859281449404,
          28.125067173193
        ],
        [
          80.859281449404,
          25.3123137367258
        ]
      ]
    ]
  },
  "bbox": [
    80.859281449404,
    25.3123137367258,
    84.3750383637184,
    28.125067173193
  ],
  "properties": {
    "datetime": "2025-03-19T00:00:00Z"
  },
  "links": [
    {
      "rel": "root",
      "href": "../../../catalog.json",
      "type": "application/json"
    },
    {
      "rel": "collection",
      "href": "../collection.json",
      "type": "application/json"
    },
    {
      "rel": "parent",
      "href": "../collection.json",
      "type": "application/json"
    }
  ],
  "assets": {
    "parquet-part-00151-591e802d-e569-443e-ac49-12b07aca9379-c000.zstd.parquet": {
      "href": "s3://overturemaps-us-west-2/release/2025-03-19.1/theme=buildings/type=building/part-00151-591e802d-e569-443e-ac49-12b07aca9379-c000.zstd.parquet",
      "type": "application/vnd.apache.parquet"
    }
  },
  "collection": "building"
}